SIGMOD/SIGMOD_CCI.py
SIGMOD/SIGMOD_SVLR.py
SIGMOD/SIGMOD_main.py
SIGMOD/SIGMOD_plot.py
SIGMOD/SIGMOD_utils.py
SIGMOD/__init__.py
sigmod-0.1.0.dist-info/licenses/LICENSE
sigmod-0.1.0.dist-info/METADATA
sigmod-0.1.0.dist-info/WHEEL
sigmod-0.1.0.dist-info/top_level.txt
sigmod-0.1.0.dist-info/RECORD
