Metadata-Version: 2.4
Name: SIGMOD
Version: 0.1.0
Summary: Deciphering microenvironment using Scalable niche guided module discovery
Author-email: liuchang <liu-chan20@mails.tsinghua.edu.cn>
Project-URL: Homepage, https://github.com/Boxedpig/SIGMOD
Project-URL: Bug Tracker, https://github.com/Boxedpig/SIGMOD/issues
Classifier: Programming Language :: Python :: 3
Classifier: License :: OSI Approved :: MIT License
Classifier: Operating System :: OS Independent
Requires-Python: ~=3.11
License-File: LICENSE
Requires-Dist: scanpy~=1.11
Requires-Dist: anndata~=0.11
Requires-Dist: torch~=2.5
Requires-Dist: entmax~=1.3
Requires-Dist: scikit-learn~=1.5
Requires-Dist: statsmodels~=0.14
Requires-Dist: numpy~=2.1
Requires-Dist: numba~=0.61.2
Requires-Dist: scipy~=1.15
Requires-Dist: pandas~=2.2
Requires-Dist: matplotlib~=3.10
Requires-Dist: seaborn~=0.13
Requires-Dist: h5py~=3.13
Requires-Dist: tqdm~=4.67
Requires-Dist: natsort~=8.4
Requires-Dist: pynndescent~=0.5
Requires-Dist: pyro-api~=0.1.2
Requires-Dist: pyro-ppl~=1.9.1
Requires-Dist: umap-learn~=0.5
Requires-Dist: networkx~=3.3
Requires-Dist: joblib~=1.5
Requires-Dist: patsy~=1.0
Requires-Dist: pillow~=11.0
Dynamic: license-file
